great_expectations/__init__.py
great_expectations/_docs_decorators.py
great_expectations/_version.py
great_expectations/alias_types.py
great_expectations/constants.py
great_expectations/py.typed
great_expectations/util.py
great_expectations/warnings.py
great_expectations/checkpoint/__init__.py
great_expectations/checkpoint/actions.py
great_expectations/checkpoint/checkpoint.py
great_expectations/compatibility/__init__.py
great_expectations/compatibility/aws.py
great_expectations/compatibility/azure.py
great_expectations/compatibility/bigquery.py
great_expectations/compatibility/databricks.py
great_expectations/compatibility/docstring_parser.py
great_expectations/compatibility/google.py
great_expectations/compatibility/not_imported.py
great_expectations/compatibility/numpy.py
great_expectations/compatibility/pandas_compatibility.py
great_expectations/compatibility/pip.py
great_expectations/compatibility/postgresql.py
great_expectations/compatibility/py4j.py
great_expectations/compatibility/pyarrow.py
great_expectations/compatibility/pydantic.py
great_expectations/compatibility/pypd.py
great_expectations/compatibility/pyspark.py
great_expectations/compatibility/snowflake.py
great_expectations/compatibility/sqlalchemy.py
great_expectations/compatibility/sqlalchemy_and_pandas.py
great_expectations/compatibility/sqlalchemy_compatibility_wrappers.py
great_expectations/compatibility/trino.py
great_expectations/compatibility/typing_extensions.py
great_expectations/core/__init__.py
great_expectations/core/batch.py
great_expectations/core/batch_definition.py
great_expectations/core/batch_manager.py
great_expectations/core/batch_spec.py
great_expectations/core/config_peer.py
great_expectations/core/config_provider.py
great_expectations/core/config_substitutor.py
great_expectations/core/configuration.py
great_expectations/core/data_context_key.py
great_expectations/core/domain.py
great_expectations/core/expectation_suite.py
great_expectations-1.10.0.dist-info/licenses/LICENSE
great_expectations-1.10.0.dist-info/METADATA
great_expectations-1.10.0.dist-info/WHEEL
great_expectations-1.10.0.dist-info/top_level.txt
great_expectations-1.10.0.dist-info/RECORD
